spdx_matcher/__init__.py
spdx_matcher/data_models.py
spdx_matcher/spdxCache.json
spdx_matcher/_pyinstaller/__init__.py
spdx_matcher/_pyinstaller/hook-spdx_matcher.py
spdx_matcher-0.1.4.dist-info/licenses/LICENSE.txt
spdx_matcher-0.1.4.dist-info/METADATA
spdx_matcher-0.1.4.dist-info/WHEEL
spdx_matcher-0.1.4.dist-info/entry_points.txt
spdx_matcher-0.1.4.dist-info/top_level.txt
spdx_matcher-0.1.4.dist-info/RECORD
