Metadata-Version: 2.4
Name: spdx_matcher
Version: 0.1.4
Summary: A package that enables extracting licenses from free text using spdx license matching algorithm
Author-email: Mike Moore <z_z_zebra@yahoo.com>
Maintainer-email: Mike Moore <z_z_zebra@yahoo.com>
License-Expression: Apache-2.0
Project-URL: Homepage, https://github.com/MikeMoore63/spdx_matcher
Project-URL: Bug Reports, https://github.com/MikeMoore63/spdx_matcher/issues
Project-URL: Source, https://github.com/MikeMoore63/spdx_matcher/
Keywords: spdx,licensedetector
Classifier: Development Status :: 3 - Alpha
Classifier: Intended Audience :: Developers
Classifier: Topic :: Software Development :: Build Tools
Classifier: Programming Language :: Python :: 3
Classifier: Programming Language :: Python :: 3.10
Classifier: Programming Language :: Python :: 3.11
Classifier: Programming Language :: Python :: 3.12
Classifier: Programming Language :: Python :: 3.13
Classifier: Programming Language :: Python :: 3.14
Classifier: Programming Language :: Python :: 3 :: Only
Requires-Python: >=3.9
License-File: LICENSE.txt
Provides-Extra: dev
Requires-Dist: check-manifest; extra == "dev"
Requires-Dist: black; extra == "dev"
Provides-Extra: test
Requires-Dist: coverage; extra == "test"
Provides-Extra: fuzzy
Requires-Dist: jellyfish~=1.0; extra == "fuzzy"
Dynamic: license-file
